{
  "db_name": "PostgreSQL",
  "query": "\n        SELECT id, user_id, expires_at, revoked\n        FROM refresh_tokens\n        WHERE token_hash = $1\n        ",
  "describe": {
    "columns": [
      {
        "ordinal": 0,
        "name": "id",
        "type_info": "Uuid"
      },
      {
        "ordinal": 1,
        "name": "user_id",
        "type_info": "Uuid"
      },
      {
        "ordinal": 2,
        "name": "expires_at",
        "type_info": "Timestamptz"
      },
      {
        "ordinal": 3,
        "name": "revoked",
        "type_info": "Bool"
      }
    ],
    "parameters": {
      "Left": [
        "Text"
      ]
    },
    "nullable": [
      false,
      false,
      false,
      false
    ]
  },
  "hash": "66f773a3f890d6414947229681286247039c5ade186c8c2721f76cd7af891e7f"
}
